.gitignore
setup.py
SpecClient/Spec.py
SpecClient/SpecArray.py
SpecClient/SpecChannel.py
SpecClient/SpecClientError.py
SpecClient/SpecCommand.py
SpecClient/SpecConnection.py
SpecClient/SpecConnectionsManager.py
SpecClient/SpecCounter.py
SpecClient/SpecEventsDispatcher.py
SpecClient/SpecMessage.py
SpecClient/SpecMotor.py
SpecClient/SpecReply.py
SpecClient/SpecScan.py
SpecClient/SpecServer.py
SpecClient/SpecVariable.py
SpecClient/SpecWaitObject.py
SpecClient/__init__.py
SpecClient/saferef.py
SpecClient_for_pyxes.egg-info/PKG-INFO
SpecClient_for_pyxes.egg-info/SOURCES.txt
SpecClient_for_pyxes.egg-info/dependency_links.txt
SpecClient_for_pyxes.egg-info/top_level.txt