Metadata-Version: 1.0
Name: SpecClient-for-pyxes
Version: 2017.3.6
Summary: Python package for communicating with spec
Home-page: UNKNOWN
Author: Matias Guijarro, BCU(Bliss), ESRF
Author-email: UNKNOWN
License: UNKNOWN
Platform: UNKNOWN
